_cffi_backend.cpython-37m-x86_64-linux-gnu.so
cffi/__init__.py
cffi/_cffi_errors.h
cffi/_cffi_include.h
cffi/_embedding.h
cffi/api.py
cffi/backend_ctypes.py
cffi/cffi_opcode.py
cffi/commontypes.py
cffi/cparser.py
cffi/error.py
cffi/ffiplatform.py
cffi/lock.py
cffi/model.py
cffi/parse_c_type.h
cffi/pkgconfig.py
cffi/recompiler.py
cffi/setuptools_ext.py
cffi/vengine_cpy.py
cffi/vengine_gen.py
cffi/verifier.py
cffi_demo-1.15.0.dist-info/LICENSE
cffi_demo-1.15.0.dist-info/METADATA
cffi_demo-1.15.0.dist-info/WHEEL
cffi_demo-1.15.0.dist-info/entry_points.txt
cffi_demo-1.15.0.dist-info/top_level.txt
cffi_demo-1.15.0.dist-info/RECORD
